Authors.rst
LICENSE.txt
MANIFEST.in
NEWS
README.md
setup.cfg
setup.py
maegatk/__init__.py
maegatk/cli.py
maegatk/maegatkHelp.py
maegatk/__pycache__/__init__.cpython-38.pyc
maegatk/__pycache__/cli.cpython-38.pyc
maegatk/__pycache__/maegatkHelp.cpython-38.pyc
maegatk/bin/fgbio.jar
maegatk/bin/picard.jar
maegatk/bin/R/toRDS.R
maegatk/bin/anno/fasta/hg19.fasta
maegatk/bin/anno/fasta/hg19.fasta.amb
maegatk/bin/anno/fasta/hg19.fasta.ann
maegatk/bin/anno/fasta/hg19.fasta.bwt
maegatk/bin/anno/fasta/hg19.fasta.pac
maegatk/bin/anno/fasta/hg19.fasta.sa
maegatk/bin/anno/fasta/rCRS.fasta
maegatk/bin/anno/fasta/rCRS.fasta.amb
maegatk/bin/anno/fasta/rCRS.fasta.ann
maegatk/bin/anno/fasta/rCRS.fasta.bwt
maegatk/bin/anno/fasta/rCRS.fasta.pac
maegatk/bin/anno/fasta/rCRS.fasta.sa
maegatk/bin/python/filterClipBam.py
maegatk/bin/python/find_barcodes.py
maegatk/bin/python/oneSample_maegatk.py
maegatk/bin/python/split_barcoded_bam.py
maegatk/bin/python/sumstatsBP.py
maegatk/bin/snake/Snakefile.maegatk.Gather
maegatk/bin/snake/Snakefile.maegatk.Scatter