Metadata-Version: 1.1
Name: maegatk
Version: 0.2.0
Summary: Processing and quality control of mitochondrial genome variants from MAESTER data.
Home-page: https://github.com/caleblareau/maegatk
Author: Caleb Lareau
Author-email: caleb.lareau@gmail.com
License: MIT
Platform: any
Classifier: Development Status :: 3 - Alpha
Classifier: Environment :: Console
Classifier: Intended Audience :: Developers
Classifier: License :: OSI Approved :: MIT License
Classifier: Operating System :: POSIX
Classifier: Operating System :: MacOS
Classifier: Operating System :: Unix
Classifier: Programming Language :: Python
Classifier: Programming Language :: Python :: 3
Classifier: Topic :: Software Development :: Libraries :: Python Modules
